Compiled from "DashScopeAudioTranscriptionApi.java"
public class com.alibaba.cloud.ai.dashscope.api.DashScopeAudioTranscriptionApi {
  public com.alibaba.cloud.ai.dashscope.api.DashScopeAudioTranscriptionApi(java.lang.String, java.lang.String, org.springframework.ai.model.ApiKey, java.lang.String, org.springframework.util.MultiValueMap<java.lang.String, java.lang.String>, org.springframework.web.client.RestClient$Builder, org.springframework.web.reactive.function.client.WebClient$Builder, org.springframework.web.client.ResponseErrorHandler);
    Code:
       0: aload_0
       1: invokespecial #3                  // Method java/lang/Object."<init>":()V
       4: aload_0
       5: aload_1
       6: putfield      #9                  // Field baseUrl:Ljava/lang/String;
       9: aload_0
      10: aload_2
      11: putfield      #15                 // Field websocketUrl:Ljava/lang/String;
      14: aload_0
      15: aload_3
      16: putfield      #18                 // Field apiKey:Lorg/springframework/ai/model/ApiKey;
      19: aload_0
      20: aload         4
      22: putfield      #22                 // Field workSpaceId:Ljava/lang/String;
      25: aload_0
      26: aload         5
      28: putfield      #25                 // Field headers:Lorg/springframework/util/MultiValueMap;
      31: aload         5
      33: aload_3
      34: invokedynamic #29,  0             // InvokeDynamic #0:accept:(Lorg/springframework/util/MultiValueMap;Lorg/springframework/ai/model/ApiKey;)Ljava/util/function/Consumer;
      39: astore        9
      41: aload_0
      42: aload         6
      44: invokeinterface #33,  1           // InterfaceMethod org/springframework/web/client/RestClient$Builder.clone:()Lorg/springframework/web/client/RestClient$Builder;
      49: aload_1
      50: invokeinterface #39,  2           // InterfaceMethod org/springframework/web/client/RestClient$Builder.baseUrl:(Ljava/lang/String;)Lorg/springframework/web/client/RestClient$Builder;
      55: aload         9
      57: invokeinterface #42,  2           // InterfaceMethod org/springframework/web/client/RestClient$Builder.defaultHeaders:(Ljava/util/function/Consumer;)Lorg/springframework/web/client/RestClient$Builder;
      62: aload         8
      64: invokeinterface #46,  2           // InterfaceMethod org/springframework/web/client/RestClient$Builder.defaultStatusHandler:(Lorg/springframework/web/client/ResponseErrorHandler;)Lorg/springframework/web/client/RestClient$Builder;
      69: invokeinterface #50,  1           // InterfaceMethod org/springframework/web/client/RestClient$Builder.build:()Lorg/springframework/web/client/RestClient;
      74: putfield      #54                 // Field restClient:Lorg/springframework/web/client/RestClient;
      77: aload_0
      78: aload         7
      80: invokeinterface #58,  1           // InterfaceMethod org/springframework/web/reactive/function/client/WebClient$Builder.clone:()Lorg/springframework/web/reactive/function/client/WebClient$Builder;
      85: aload_1
      86: invokeinterface #63,  2           // InterfaceMethod org/springframework/web/reactive/function/client/WebClient$Builder.baseUrl:(Ljava/lang/String;)Lorg/springframework/web/reactive/function/client/WebClient$Builder;
      91: aload         9
      93: invokeinterface #66,  2           // InterfaceMethod org/springframework/web/reactive/function/client/WebClient$Builder.defaultHeaders:(Ljava/util/function/Consumer;)Lorg/springframework/web/reactive/function/client/WebClient$Builder;
      98: invokeinterface #69,  1           // InterfaceMethod org/springframework/web/reactive/function/client/WebClient$Builder.build:()Lorg/springframework/web/reactive/function/client/WebClient;
     103: putfield      #72                 // Field webClient:Lorg/springframework/web/reactive/function/client/WebClient;
     106: aload_0
     107: invokestatic  #76                 // Method com/alibaba/cloud/ai/dashscope/api/asr/DashScopeWebSocketAsrApi.builder:()Lcom/alibaba/cloud/ai/dashscope/api/asr/DashScopeWebSocketAsrApi$Builder;
     110: invokestatic  #82                 // Method com/alibaba/cloud/ai/dashscope/protocol/DashScopeWebSocketClientOptions.builder:()Lcom/alibaba/cloud/ai/dashscope/protocol/DashScopeWebSocketClientOptions$Builder;
     113: aload_3
     114: invokeinterface #87,  1           // InterfaceMethod org/springframework/ai/model/ApiKey.getValue:()Ljava/lang/String;
     119: invokevirtual #93                 // Method com/alibaba/cloud/ai/dashscope/protocol/DashScopeWebSocketClientOptions$Builder.apiKey:(Ljava/lang/String;)Lcom/alibaba/cloud/ai/dashscope/protocol/DashScopeWebSocketClientOptions$Builder;
     122: aload         4
     124: invokevirtual #98                 // Method com/alibaba/cloud/ai/dashscope/protocol/DashScopeWebSocketClientOptions$Builder.workSpaceId:(Ljava/lang/String;)Lcom/alibaba/cloud/ai/dashscope/protocol/DashScopeWebSocketClientOptions$Builder;
     127: aload_2
     128: invokevirtual #100                // Method com/alibaba/cloud/ai/dashscope/protocol/DashScopeWebSocketClientOptions$Builder.url:(Ljava/lang/String;)Lcom/alibaba/cloud/ai/dashscope/protocol/DashScopeWebSocketClientOptions$Builder;
     131: invokevirtual #103                // Method com/alibaba/cloud/ai/dashscope/protocol/DashScopeWebSocketClientOptions$Builder.build:()Lcom/alibaba/cloud/ai/dashscope/protocol/DashScopeWebSocketClientOptions;
     134: invokevirtual #106                // Method com/alibaba/cloud/ai/dashscope/api/asr/DashScopeWebSocketAsrApi$Builder.options:(Lcom/alibaba/cloud/ai/dashscope/protocol/DashScopeWebSocketClientOptions;)Lcom/alibaba/cloud/ai/dashscope/api/asr/DashScopeWebSocketAsrApi$Builder;
     137: invokevirtual #112                // Method com/alibaba/cloud/ai/dashscope/api/asr/DashScopeWebSocketAsrApi$Builder.build:()Lcom/alibaba/cloud/ai/dashscope/api/asr/DashScopeWebSocketAsrApi;
     140: putfield      #115                // Field webSocketAsrApi:Lcom/alibaba/cloud/ai/dashscope/api/asr/DashScopeWebSocketAsrApi;
     143: aload_0
     144: invokestatic  #119                // Method com/fasterxml/jackson/databind/json/JsonMapper.builder:()Lcom/fasterxml/jackson/databind/json/JsonMapper$Builder;
     147: iconst_1
     148: anewarray     #124                // class com/fasterxml/jackson/databind/DeserializationFeature
     151: dup
     152: iconst_0
     153: getstatic     #126                // Field com/fasterxml/jackson/databind/DeserializationFeature.FAIL_ON_UNKNOWN_PROPERTIES:Lcom/fasterxml/jackson/databind/DeserializationFeature;
     156: aastore
     157: invokevirtual #130                // Method com/fasterxml/jackson/databind/json/JsonMapper$Builder.disable:([Lcom/fasterxml/jackson/databind/DeserializationFeature;)Lcom/fasterxml/jackson/databind/cfg/MapperBuilder;
     160: checkcast     #131                // class com/fasterxml/jackson/databind/json/JsonMapper$Builder
     163: iconst_1
     164: anewarray     #136                // class com/fasterxml/jackson/databind/SerializationFeature
     167: dup
     168: iconst_0
     169: getstatic     #138                // Field com/fasterxml/jackson/databind/SerializationFeature.FAIL_ON_EMPTY_BEANS:Lcom/fasterxml/jackson/databind/SerializationFeature;
     172: aastore
     173: invokevirtual #142                // Method com/fasterxml/jackson/databind/json/JsonMapper$Builder.disable:([Lcom/fasterxml/jackson/databind/SerializationFeature;)Lcom/fasterxml/jackson/databind/cfg/MapperBuilder;
     176: checkcast     #131                // class com/fasterxml/jackson/databind/json/JsonMapper$Builder
     179: iconst_1
     180: anewarray     #136                // class com/fasterxml/jackson/databind/SerializationFeature
     183: dup
     184: iconst_0
     185: getstatic     #145                // Field com/fasterxml/jackson/databind/SerializationFeature.WRITE_DATES_AS_TIMESTAMPS:Lcom/fasterxml/jackson/databind/SerializationFeature;
     188: aastore
     189: invokevirtual #142                // Method com/fasterxml/jackson/databind/json/JsonMapper$Builder.disable:([Lcom/fasterxml/jackson/databind/SerializationFeature;)Lcom/fasterxml/jackson/databind/cfg/MapperBuilder;
     192: checkcast     #131                // class com/fasterxml/jackson/databind/json/JsonMapper$Builder
     195: getstatic     #148                // Field com/fasterxml/jackson/annotation/JsonInclude$Include.NON_NULL:Lcom/fasterxml/jackson/annotation/JsonInclude$Include;
     198: invokevirtual #154                // Method com/fasterxml/jackson/databind/json/JsonMapper$Builder.serializationInclusion:(Lcom/fasterxml/jackson/annotation/JsonInclude$Include;)Lcom/fasterxml/jackson/databind/cfg/MapperBuilder;
     201: checkcast     #131                // class com/fasterxml/jackson/databind/json/JsonMapper$Builder
     204: invokestatic  #158                // Method org/springframework/ai/util/JacksonUtils.instantiateAvailableModules:()Ljava/util/List;
     207: invokevirtual #164                // Method com/fasterxml/jackson/databind/json/JsonMapper$Builder.addModules:(Ljava/lang/Iterable;)Lcom/fasterxml/jackson/databind/cfg/MapperBuilder;
     210: checkcast     #131                // class com/fasterxml/jackson/databind/json/JsonMapper$Builder
     213: invokevirtual #168                // Method com/fasterxml/jackson/databind/json/JsonMapper$Builder.build:()Lcom/fasterxml/jackson/databind/ObjectMapper;
     216: putfield      #171                // Field objectMapper:Lcom/fasterxml/jackson/databind/ObjectMapper;
     219: return

  public org.springframework.ai.audio.transcription.AudioTranscriptionResponse callLiveTranslate(com.alibaba.cloud.ai.dashscope.audio.transcription.DashScopeAudioTranscriptionPrompt, com.alibaba.cloud.ai.dashscope.audio.transcription.DashScopeAudioTranscriptionOptions);
    Code:
       0: invokestatic  #175                // Method com/alibaba/cloud/ai/dashscope/audio/transcription/DashScopeTranscriptionApiSpec$DashScopeAudioTranscriptionRequest.builder:()Lcom/alibaba/cloud/ai/dashscope/audio/transcription/DashScopeTranscriptionApiSpec$DashScopeAudioTranscriptionRequest$Builder;
       3: aload_2
       4: invokevirtual #180                // Method com/alibaba/cloud/ai/dashscope/audio/transcription/DashScopeAudioTranscriptionOptions.getModel:()Ljava/lang/String;
       7: invokevirtual #185                // Method com/alibaba/cloud/ai/dashscope/audio/transcription/DashScopeTranscriptionApiSpec$DashScopeAudioTranscriptionRequest$Builder.model:(Ljava/lang/String;)Lcom/alibaba/cloud/ai/dashscope/audio/transcription/DashScopeTranscriptionApiSpec$DashScopeAudioTranscriptionRequest$Builder;
      10: aload_1
      11: invokevirtual #191                // Method com/alibaba/cloud/ai/dashscope/audio/transcription/DashScopeAudioTranscriptionPrompt.getMessages:()Ljava/util/List;
      14: invokevirtual #196                // Method com/alibaba/cloud/ai/dashscope/audio/transcription/DashScopeTranscriptionApiSpec$DashScopeAudioTranscriptionRequest$Builder.messages:(Ljava/util/List;)Lcom/alibaba/cloud/ai/dashscope/audio/transcription/DashScopeTranscriptionApiSpec$DashScopeAudioTranscriptionRequest$Builder;
      17: aload_2
      18: invokevirtual #200                // Method com/alibaba/cloud/ai/dashscope/audio/transcription/DashScopeAudioTranscriptionOptions.getModalities:()Ljava/util/List;
      21: invokevirtual #203                // Method com/alibaba/cloud/ai/dashscope/audio/transcription/DashScopeTranscriptionApiSpec$DashScopeAudioTranscriptionRequest$Builder.modalities:(Ljava/util/List;)Lcom/alibaba/cloud/ai/dashscope/audio/transcription/DashScopeTranscriptionApiSpec$DashScopeAudioTranscriptionRequest$Builder;
      24: iconst_0
      25: invokestatic  #206                // Method java/lang/Boolean.valueOf:(Z)Ljava/lang/Boolean;
      28: invokevirtual #212                // Method com/alibaba/cloud/ai/dashscope/audio/transcription/DashScopeTranscriptionApiSpec$DashScopeAudioTranscriptionRequest$Builder.stream:(Ljava/lang/Boolean;)Lcom/alibaba/cloud/ai/dashscope/audio/transcription/DashScopeTranscriptionApiSpec$DashScopeAudioTranscriptionRequest$Builder;
      31: aload_2
      32: invokevirtual #216                // Method com/alibaba/cloud/ai/dashscope/audio/transcription/DashScopeAudioTranscriptionOptions.getAudio:()Lcom/alibaba/cloud/ai/dashscope/audio/transcription/DashScopeAudioTranscriptionOptions$Audio;
      35: invokevirtual #220                // Method com/alibaba/cloud/ai/dashscope/audio/transcription/DashScopeTranscriptionApiSpec$DashScopeAudioTranscriptionRequest$Builder.audio:(Lcom/alibaba/cloud/ai/dashscope/audio/transcription/DashScopeAudioTranscriptionOptions$Audio;)Lcom/alibaba/cloud/ai/dashscope/audio/transcription/DashScopeTranscriptionApiSpec$DashScopeAudioTranscriptionRequest$Builder;
      38: aload_2
      39: invokevirtual #224                // Method com/alibaba/cloud/ai/dashscope/audio/transcription/DashScopeAudioTranscriptionOptions.getMaxTokens:()Ljava/lang/Integer;
      42: invokevirtual #228                // Method com/alibaba/cloud/ai/dashscope/audio/transcription/DashScopeTranscriptionApiSpec$DashScopeAudioTranscriptionRequest$Builder.maxTokens:(Ljava/lang/Integer;)Lcom/alibaba/cloud/ai/dashscope/audio/transcription/DashScopeTranscriptionApiSpec$DashScopeAudioTranscriptionRequest$Builder;
      45: aload_2
      46: invokevirtual #232                // Method com/alibaba/cloud/ai/dashscope/audio/transcription/DashScopeAudioTranscriptionOptions.getSeed:()Ljava/lang/Integer;
      49: invokevirtual #235                // Method com/alibaba/cloud/ai/dashscope/audio/transcription/DashScopeTranscriptionApiSpec$DashScopeAudioTranscriptionRequest$Builder.seed:(Ljava/lang/Integer;)Lcom/alibaba/cloud/ai/dashscope/audio/transcription/DashScopeTranscriptionApiSpec$DashScopeAudioTranscriptionRequest$Builder;
      52: aload_2
      53: invokevirtual #238                // Method com/alibaba/cloud/ai/dashscope/audio/transcription/DashScopeAudioTranscriptionOptions.getTemperature:()Ljava/lang/Float;
      56: invokevirtual #242                // Method com/alibaba/cloud/ai/dashscope/audio/transcription/DashScopeTranscriptionApiSpec$DashScopeAudioTranscriptionRequest$Builder.temperature:(Ljava/lang/Float;)Lcom/alibaba/cloud/ai/dashscope/audio/transcription/DashScopeTranscriptionApiSpec$DashScopeAudioTranscriptionRequest$Builder;
      59: aload_2
      60: invokevirtual #246                // Method com/alibaba/cloud/ai/dashscope/audio/transcription/DashScopeAudioTranscriptionOptions.getTopP:()Ljava/lang/Float;
      63: invokevirtual #249                // Method com/alibaba/cloud/ai/dashscope/audio/transcription/DashScopeTranscriptionApiSpec$DashScopeAudioTranscriptionRequest$Builder.topP:(Ljava/lang/Float;)Lcom/alibaba/cloud/ai/dashscope/audio/transcription/DashScopeTranscriptionApiSpec$DashScopeAudioTranscriptionRequest$Builder;
      66: aload_2
      67: invokevirtual #252                // Method com/alibaba/cloud/ai/dashscope/audio/transcription/DashScopeAudioTranscriptionOptions.getPresencePenalty:()Ljava/lang/Float;
      70: invokevirtual #255                // Method com/alibaba/cloud/ai/dashscope/audio/transcription/DashScopeTranscriptionApiSpec$DashScopeAudioTranscriptionRequest$Builder.presencePenalty:(Ljava/lang/Float;)Lcom/alibaba/cloud/ai/dashscope/audio/transcription/DashScopeTranscriptionApiSpec$DashScopeAudioTranscriptionRequest$Builder;
      73: aload_2
      74: invokevirtual #258                // Method com/alibaba/cloud/ai/dashscope/audio/transcription/DashScopeAudioTranscriptionOptions.getTopK:()Ljava/lang/Integer;
      77: invokevirtual #261                // Method com/alibaba/cloud/ai/dashscope/audio/transcription/DashScopeTranscriptionApiSpec$DashScopeAudioTranscriptionRequest$Builder.topK:(Ljava/lang/Integer;)Lcom/alibaba/cloud/ai/dashscope/audio/transcription/DashScopeTranscriptionApiSpec$DashScopeAudioTranscriptionRequest$Builder;
      80: aload_2
      81: invokevirtual #264                // Method com/alibaba/cloud/ai/dashscope/audio/transcription/DashScopeAudioTranscriptionOptions.getRepetitionPenalty:()Ljava/lang/Float;
      84: invokevirtual #267                // Method com/alibaba/cloud/ai/dashscope/audio/transcription/DashScopeTranscriptionApiSpec$DashScopeAudioTranscriptionRequest$Builder.repetitionPenalty:(Ljava/lang/Float;)Lcom/alibaba/cloud/ai/dashscope/audio/transcription/DashScopeTranscriptionApiSpec$DashScopeAudioTranscriptionRequest$Builder;
      87: aload_2
      88: invokevirtual #270                // Method com/alibaba/cloud/ai/dashscope/audio/transcription/DashScopeAudioTranscriptionOptions.getTranslationOptions:()Lcom/alibaba/cloud/ai/dashscope/audio/transcription/DashScopeAudioTranscriptionOptions$TranslationOptions;
      91: invokevirtual #274                // Method com/alibaba/cloud/ai/dashscope/audio/transcription/DashScopeTranscriptionApiSpec$DashScopeAudioTranscriptionRequest$Builder.translationOptions:(Lcom/alibaba/cloud/ai/dashscope/audio/transcription/DashScopeAudioTranscriptionOptions$TranslationOptions;)Lcom/alibaba/cloud/ai/dashscope/audio/transcription/DashScopeTranscriptionApiSpec$DashScopeAudioTranscriptionRequest$Builder;
      94: invokevirtual #278                // Method com/alibaba/cloud/ai/dashscope/audio/transcription/DashScopeTranscriptionApiSpec$DashScopeAudioTranscriptionRequest$Builder.build:()Lcom/alibaba/cloud/ai/dashscope/audio/transcription/DashScopeTranscriptionApiSpec$DashScopeAudioTranscriptionRequest;
      97: astore_3
      98: aload_0
      99: getfield      #54                 // Field restClient:Lorg/springframework/web/client/RestClient;
     102: invokeinterface #281,  1          // InterfaceMethod org/springframework/web/client/RestClient.post:()Lorg/springframework/web/client/RestClient$RequestBodyUriSpec;
     107: ldc_w         #289                // String /compatible-mode/v1/chat/completions
     110: iconst_0
     111: anewarray     #4                  // class java/lang/Object
     114: invokeinterface #291,  3          // InterfaceMethod org/springframework/web/client/RestClient$RequestBodyUriSpec.uri:(Ljava/lang/String;[Ljava/lang/Object;)Lorg/springframework/web/client/RestClient$RequestHeadersSpec;
     119: checkcast     #297                // class org/springframework/web/client/RestClient$RequestBodySpec
     122: aload_3
     123: invokeinterface #299,  2          // InterfaceMethod org/springframework/web/client/RestClient$RequestBodySpec.body:(Ljava/lang/Object;)Lorg/springframework/web/client/RestClient$RequestBodySpec;
     128: invokeinterface #303,  1          // InterfaceMethod org/springframework/web/client/RestClient$RequestBodySpec.retrieve:()Lorg/springframework/web/client/RestClient$ResponseSpec;
     133: ldc_w         #307                // class com/alibaba/cloud/ai/dashscope/audio/transcription/DashScopeTranscriptionApiSpec$DashScopeAudioTranscriptionResponse
     136: invokeinterface #309,  2          // InterfaceMethod org/springframework/web/client/RestClient$ResponseSpec.toEntity:(Ljava/lang/Class;)Lorg/springframework/http/ResponseEntity;
     141: astore        4
     143: aload         4
     145: invokevirtual #315                // Method org/springframework/http/ResponseEntity.getStatusCode:()Lorg/springframework/http/HttpStatusCode;
     148: invokeinterface #321,  1          // InterfaceMethod org/springframework/http/HttpStatusCode.is2xxSuccessful:()Z
     153: ifeq          165
     156: aload         4
     158: invokevirtual #327                // Method org/springframework/http/ResponseEntity.getBody:()Ljava/lang/Object;
     161: checkcast     #331                // class org/springframework/ai/audio/transcription/AudioTranscriptionResponse
     164: areturn
     165: getstatic     #333                // Field log:Lorg/slf4j/Logger;
     168: aload         4
     170: invokevirtual #315                // Method org/springframework/http/ResponseEntity.getStatusCode:()Lorg/springframework/http/HttpStatusCode;
     173: invokedynamic #337,  0            // InvokeDynamic #1:makeConcatWithConstants:(Lorg/springframework/http/HttpStatusCode;)Ljava/lang/String;
     178: invokeinterface #341,  2          // InterfaceMethod org/slf4j/Logger.error:(Ljava/lang/String;)V
     183: new           #347                // class java/lang/RuntimeException
     186: dup
     187: aload         4
     189: invokevirtual #315                // Method org/springframework/http/ResponseEntity.getStatusCode:()Lorg/springframework/http/HttpStatusCode;
     192: invokedynamic #337,  0            // InvokeDynamic #1:makeConcatWithConstants:(Lorg/springframework/http/HttpStatusCode;)Ljava/lang/String;
     197: invokespecial #349                // Method java/lang/RuntimeException."<init>":(Ljava/lang/String;)V
     200: athrow

  public reactor.core.publisher.Flux<org.springframework.ai.audio.transcription.AudioTranscriptionResponse> streamLiveTranslate(com.alibaba.cloud.ai.dashscope.audio.transcription.DashScopeAudioTranscriptionPrompt, com.alibaba.cloud.ai.dashscope.audio.transcription.DashScopeAudioTranscriptionOptions);
    Code:
       0: invokestatic  #175                // Method com/alibaba/cloud/ai/dashscope/audio/transcription/DashScopeTranscriptionApiSpec$DashScopeAudioTranscriptionRequest.builder:()Lcom/alibaba/cloud/ai/dashscope/audio/transcription/DashScopeTranscriptionApiSpec$DashScopeAudioTranscriptionRequest$Builder;
       3: aload_2
       4: invokevirtual #180                // Method com/alibaba/cloud/ai/dashscope/audio/transcription/DashScopeAudioTranscriptionOptions.getModel:()Ljava/lang/String;
       7: invokevirtual #185                // Method com/alibaba/cloud/ai/dashscope/audio/transcription/DashScopeTranscriptionApiSpec$DashScopeAudioTranscriptionRequest$Builder.model:(Ljava/lang/String;)Lcom/alibaba/cloud/ai/dashscope/audio/transcription/DashScopeTranscriptionApiSpec$DashScopeAudioTranscriptionRequest$Builder;
      10: aload_1
      11: invokevirtual #191                // Method com/alibaba/cloud/ai/dashscope/audio/transcription/DashScopeAudioTranscriptionPrompt.getMessages:()Ljava/util/List;
      14: invokevirtual #196                // Method com/alibaba/cloud/ai/dashscope/audio/transcription/DashScopeTranscriptionApiSpec$DashScopeAudioTranscriptionRequest$Builder.messages:(Ljava/util/List;)Lcom/alibaba/cloud/ai/dashscope/audio/transcription/DashScopeTranscriptionApiSpec$DashScopeAudioTranscriptionRequest$Builder;
      17: aload_2
      18: invokevirtual #200                // Method com/alibaba/cloud/ai/dashscope/audio/transcription/DashScopeAudioTranscriptionOptions.getModalities:()Ljava/util/List;
      21: invokevirtual #203                // Method com/alibaba/cloud/ai/dashscope/audio/transcription/DashScopeTranscriptionApiSpec$DashScopeAudioTranscriptionRequest$Builder.modalities:(Ljava/util/List;)Lcom/alibaba/cloud/ai/dashscope/audio/transcription/DashScopeTranscriptionApiSpec$DashScopeAudioTranscriptionRequest$Builder;
      24: iconst_1
      25: invokestatic  #206                // Method java/lang/Boolean.valueOf:(Z)Ljava/lang/Boolean;
      28: invokevirtual #212                // Method com/alibaba/cloud/ai/dashscope/audio/transcription/DashScopeTranscriptionApiSpec$DashScopeAudioTranscriptionRequest$Builder.stream:(Ljava/lang/Boolean;)Lcom/alibaba/cloud/ai/dashscope/audio/transcription/DashScopeTranscriptionApiSpec$DashScopeAudioTranscriptionRequest$Builder;
      31: aload_2
      32: invokevirtual #351                // Method com/alibaba/cloud/ai/dashscope/audio/transcription/DashScopeAudioTranscriptionOptions.getStreamOptions:()Lcom/alibaba/cloud/ai/dashscope/audio/transcription/DashScopeAudioTranscriptionOptions$StreamOptions;
      35: invokevirtual #355                // Method com/alibaba/cloud/ai/dashscope/audio/transcription/DashScopeTranscriptionApiSpec$DashScopeAudioTranscriptionRequest$Builder.streamOptions:(Lcom/alibaba/cloud/ai/dashscope/audio/transcription/DashScopeAudioTranscriptionOptions$StreamOptions;)Lcom/alibaba/cloud/ai/dashscope/audio/transcription/DashScopeTranscriptionApiSpec$DashScopeAudioTranscriptionRequest$Builder;
      38: aload_2
      39: invokevirtual #216                // Method com/alibaba/cloud/ai/dashscope/audio/transcription/DashScopeAudioTranscriptionOptions.getAudio:()Lcom/alibaba/cloud/ai/dashscope/audio/transcription/DashScopeAudioTranscriptionOptions$Audio;
      42: invokevirtual #220                // Method com/alibaba/cloud/ai/dashscope/audio/transcription/DashScopeTranscriptionApiSpec$DashScopeAudioTranscriptionRequest$Builder.audio:(Lcom/alibaba/cloud/ai/dashscope/audio/transcription/DashScopeAudioTranscriptionOptions$Audio;)Lcom/alibaba/cloud/ai/dashscope/audio/transcription/DashScopeTranscriptionApiSpec$DashScopeAudioTranscriptionRequest$Builder;
      45: aload_2
      46: invokevirtual #224                // Method com/alibaba/cloud/ai/dashscope/audio/transcription/DashScopeAudioTranscriptionOptions.getMaxTokens:()Ljava/lang/Integer;
      49: invokevirtual #228                // Method com/alibaba/cloud/ai/dashscope/audio/transcription/DashScopeTranscriptionApiSpec$DashScopeAudioTranscriptionRequest$Builder.maxTokens:(Ljava/lang/Integer;)Lcom/alibaba/cloud/ai/dashscope/audio/transcription/DashScopeTranscriptionApiSpec$DashScopeAudioTranscriptionRequest$Builder;
      52: aload_2
      53: invokevirtual #232                // Method com/alibaba/cloud/ai/dashscope/audio/transcription/DashScopeAudioTranscriptionOptions.getSeed:()Ljava/lang/Integer;
      56: invokevirtual #235                // Method com/alibaba/cloud/ai/dashscope/audio/transcription/DashScopeTranscriptionApiSpec$DashScopeAudioTranscriptionRequest$Builder.seed:(Ljava/lang/Integer;)Lcom/alibaba/cloud/ai/dashscope/audio/transcription/DashScopeTranscriptionApiSpec$DashScopeAudioTranscriptionRequest$Builder;
      59: aload_2
      60: invokevirtual #238                // Method com/alibaba/cloud/ai/dashscope/audio/transcription/DashScopeAudioTranscriptionOptions.getTemperature:()Ljava/lang/Float;
      63: invokevirtual #242                // Method com/alibaba/cloud/ai/dashscope/audio/transcription/DashScopeTranscriptionApiSpec$DashScopeAudioTranscriptionRequest$Builder.temperature:(Ljava/lang/Float;)Lcom/alibaba/cloud/ai/dashscope/audio/transcription/DashScopeTranscriptionApiSpec$DashScopeAudioTranscriptionRequest$Builder;
      66: aload_2
      67: invokevirtual #246                // Method com/alibaba/cloud/ai/dashscope/audio/transcription/DashScopeAudioTranscriptionOptions.getTopP:()Ljava/lang/Float;
      70: invokevirtual #249                // Method com/alibaba/cloud/ai/dashscope/audio/transcription/DashScopeTranscriptionApiSpec$DashScopeAudioTranscriptionRequest$Builder.topP:(Ljava/lang/Float;)Lcom/alibaba/cloud/ai/dashscope/audio/transcription/DashScopeTranscriptionApiSpec$DashScopeAudioTranscriptionRequest$Builder;
      73: aload_2
      74: invokevirtual #252                // Method com/alibaba/cloud/ai/dashscope/audio/transcription/DashScopeAudioTranscriptionOptions.getPresencePenalty:()Ljava/lang/Float;
      77: invokevirtual #255                // Method com/alibaba/cloud/ai/dashscope/audio/transcription/DashScopeTranscriptionApiSpec$DashScopeAudioTranscriptionRequest$Builder.presencePenalty:(Ljava/lang/Float;)Lcom/alibaba/cloud/ai/dashscope/audio/transcription/DashScopeTranscriptionApiSpec$DashScopeAudioTranscriptionRequest$Builder;
      80: aload_2
      81: invokevirtual #258                // Method com/alibaba/cloud/ai/dashscope/audio/transcription/DashScopeAudioTranscriptionOptions.getTopK:()Ljava/lang/Integer;
      84: invokevirtual #261                // Method com/alibaba/cloud/ai/dashscope/audio/transcription/DashScopeTranscriptionApiSpec$DashScopeAudioTranscriptionRequest$Builder.topK:(Ljava/lang/Integer;)Lcom/alibaba/cloud/ai/dashscope/audio/transcription/DashScopeTranscriptionApiSpec$DashScopeAudioTranscriptionRequest$Builder;
      87: aload_2
      88: invokevirtual #264                // Method com/alibaba/cloud/ai/dashscope/audio/transcription/DashScopeAudioTranscriptionOptions.getRepetitionPenalty:()Ljava/lang/Float;
      91: invokevirtual #267                // Method com/alibaba/cloud/ai/dashscope/audio/transcription/DashScopeTranscriptionApiSpec$DashScopeAudioTranscriptionRequest$Builder.repetitionPenalty:(Ljava/lang/Float;)Lcom/alibaba/cloud/ai/dashscope/audio/transcription/DashScopeTranscriptionApiSpec$DashScopeAudioTranscriptionRequest$Builder;
      94: aload_2
      95: invokevirtual #270                // Method com/alibaba/cloud/ai/dashscope/audio/transcription/DashScopeAudioTranscriptionOptions.getTranslationOptions:()Lcom/alibaba/cloud/ai/dashscope/audio/transcription/DashScopeAudioTranscriptionOptions$TranslationOptions;
      98: invokevirtual #274                // Method com/alibaba/cloud/ai/dashscope/audio/transcription/DashScopeTranscriptionApiSpec$DashScopeAudioTranscriptionRequest$Builder.translationOptions:(Lcom/alibaba/cloud/ai/dashscope/audio/transcription/DashScopeAudioTranscriptionOptions$TranslationOptions;)Lcom/alibaba/cloud/ai/dashscope/audio/transcription/DashScopeTranscriptionApiSpec$DashScopeAudioTranscriptionRequest$Builder;
     101: invokevirtual #278                // Method com/alibaba/cloud/ai/dashscope/audio/transcription/DashScopeTranscriptionApiSpec$DashScopeAudioTranscriptionRequest$Builder.build:()Lcom/alibaba/cloud/ai/dashscope/audio/transcription/DashScopeTranscriptionApiSpec$DashScopeAudioTranscriptionRequest;
     104: astore_3
     105: ldc_w         #359                // String [DONE]
     108: invokedynamic #361,  0            // InvokeDynamic #2:test:(Ljava/lang/String;)Ljava/util/function/Predicate;
     113: astore        4
     115: aload_0
     116: getfield      #72                 // Field webClient:Lorg/springframework/web/reactive/function/client/WebClient;
     119: invokeinterface #365,  1          // InterfaceMethod org/springframework/web/reactive/function/client/WebClient.post:()Lorg/springframework/web/reactive/function/client/WebClient$RequestBodyUriSpec;
     124: ldc_w         #289                // String /compatible-mode/v1/chat/completions
     127: iconst_0
     128: anewarray     #4                  // class java/lang/Object
     131: invokeinterface #370,  3          // InterfaceMethod org/springframework/web/reactive/function/client/WebClient$RequestBodyUriSpec.uri:(Ljava/lang/String;[Ljava/lang/Object;)Lorg/springframework/web/reactive/function/client/WebClient$RequestHeadersSpec;
     136: checkcast     #375                // class org/springframework/web/reactive/function/client/WebClient$RequestBodySpec
     139: aload_3
     140: invokestatic  #377                // Method reactor/core/publisher/Mono.just:(Ljava/lang/Object;)Lreactor/core/publisher/Mono;
     143: ldc_w         #383                // class com/alibaba/cloud/ai/dashscope/audio/tts/DashScopeTTSApiSpec$DashScopeAudioTTSRequest
     146: invokeinterface #385,  3          // InterfaceMethod org/springframework/web/reactive/function/client/WebClient$RequestBodySpec.body:(Ljava/lang/Object;Ljava/lang/Class;)Lorg/springframework/web/reactive/function/client/WebClient$RequestHeadersSpec;
     151: invokeinterface #388,  1          // InterfaceMethod org/springframework/web/reactive/function/client/WebClient$RequestHeadersSpec.retrieve:()Lorg/springframework/web/reactive/function/client/WebClient$ResponseSpec;
     156: ldc_w         #393                // class java/lang/String
     159: invokeinterface #395,  2          // InterfaceMethod org/springframework/web/reactive/function/client/WebClient$ResponseSpec.bodyToFlux:(Ljava/lang/Class;)Lreactor/core/publisher/Flux;
     164: aload         4
     166: invokevirtual #401                // Method reactor/core/publisher/Flux.takeUntil:(Ljava/util/function/Predicate;)Lreactor/core/publisher/Flux;
     169: aload         4
     171: invokeinterface #407,  1          // InterfaceMethod java/util/function/Predicate.negate:()Ljava/util/function/Predicate;
     176: invokevirtual #413                // Method reactor/core/publisher/Flux.filter:(Ljava/util/function/Predicate;)Lreactor/core/publisher/Flux;
     179: aload_0
     180: invokedynamic #416,  0            // InvokeDynamic #3:apply:(Lcom/alibaba/cloud/ai/dashscope/api/DashScopeAudioTranscriptionApi;)Ljava/util/function/Function;
     185: invokevirtual #420                // Method reactor/core/publisher/Flux.map:(Ljava/util/function/Function;)Lreactor/core/publisher/Flux;
     188: areturn

  public reactor.core.publisher.Flux<java.lang.String> createWebSocketTask(java.nio.ByteBuffer, com.alibaba.cloud.ai.dashscope.audio.transcription.DashScopeAudioTranscriptionOptions);
    Code:
       0: aload_0
       1: getfield      #115                // Field webSocketAsrApi:Lcom/alibaba/cloud/ai/dashscope/api/asr/DashScopeWebSocketAsrApi;
       4: aload_1
       5: aload_2
       6: invokevirtual #424                // Method com/alibaba/cloud/ai/dashscope/api/asr/DashScopeWebSocketAsrApi.stream:(Ljava/nio/ByteBuffer;Lcom/alibaba/cloud/ai/dashscope/audio/transcription/DashScopeAudioTranscriptionOptions;)Lreactor/core/publisher/Flux;
       9: areturn

  public reactor.core.publisher.Flux<java.lang.String> createWebSocketStreamingTask(reactor.core.publisher.Flux<java.nio.ByteBuffer>, com.alibaba.cloud.ai.dashscope.audio.transcription.DashScopeAudioTranscriptionOptions);
    Code:
       0: aload_0
       1: getfield      #115                // Field webSocketAsrApi:Lcom/alibaba/cloud/ai/dashscope/api/asr/DashScopeWebSocketAsrApi;
       4: aload_1
       5: aload_2
       6: invokevirtual #427                // Method com/alibaba/cloud/ai/dashscope/api/asr/DashScopeWebSocketAsrApi.stream:(Lreactor/core/publisher/Flux;Lcom/alibaba/cloud/ai/dashscope/audio/transcription/DashScopeAudioTranscriptionOptions;)Lreactor/core/publisher/Flux;
       9: areturn

  public org.springframework.ai.audio.transcription.AudioTranscriptionResponse callAsr(com.alibaba.cloud.ai.dashscope.audio.transcription.DashScopeAudioTranscriptionPrompt, com.alibaba.cloud.ai.dashscope.audio.transcription.DashScopeAudioTranscriptionOptions);
    Code:
       0: invokestatic  #430                // Method com/alibaba/cloud/ai/dashscope/audio/transcription/DashScopeAsrTranscriptionApiSpec$AsrTranscriptionRequest.builder:()Lcom/alibaba/cloud/ai/dashscope/audio/transcription/DashScopeAsrTranscriptionApiSpec$AsrTranscriptionRequest$Builder;
       3: aload_2
       4: invokevirtual #180                // Method com/alibaba/cloud/ai/dashscope/audio/transcription/DashScopeAudioTranscriptionOptions.getModel:()Ljava/lang/String;
       7: invokevirtual #435                // Method com/alibaba/cloud/ai/dashscope/audio/transcription/DashScopeAsrTranscriptionApiSpec$AsrTranscriptionRequest$Builder.model:(Ljava/lang/String;)Lcom/alibaba/cloud/ai/dashscope/audio/transcription/DashScopeAsrTranscriptionApiSpec$AsrTranscriptionRequest$Builder;
      10: invokestatic  #440                // Method com/alibaba/cloud/ai/dashscope/audio/transcription/DashScopeAsrTranscriptionApiSpec$AsrTranscriptionRequest$Input.builder:()Lcom/alibaba/cloud/ai/dashscope/audio/transcription/DashScopeAsrTranscriptionApiSpec$AsrTranscriptionRequest$Input$Builder;
      13: aload_1
      14: invokevirtual #445                // Method com/alibaba/cloud/ai/dashscope/audio/transcription/DashScopeAudioTranscriptionPrompt.getFileUrls:()Ljava/util/List;
      17: invokevirtual #448                // Method com/alibaba/cloud/ai/dashscope/audio/transcription/DashScopeAsrTranscriptionApiSpec$AsrTranscriptionRequest$Input$Builder.fileUrls:(Ljava/util/List;)Lcom/alibaba/cloud/ai/dashscope/audio/transcription/DashScopeAsrTranscriptionApiSpec$AsrTranscriptionRequest$Input$Builder;
      20: invokevirtual #454                // Method com/alibaba/cloud/ai/dashscope/audio/transcription/DashScopeAsrTranscriptionApiSpec$AsrTranscriptionRequest$Input$Builder.build:()Lcom/alibaba/cloud/ai/dashscope/audio/transcription/DashScopeAsrTranscriptionApiSpec$AsrTranscriptionRequest$Input;
      23: invokevirtual #457                // Method com/alibaba/cloud/ai/dashscope/audio/transcription/DashScopeAsrTranscriptionApiSpec$AsrTranscriptionRequest$Builder.input:(Lcom/alibaba/cloud/ai/dashscope/audio/transcription/DashScopeAsrTranscriptionApiSpec$AsrTranscriptionRequest$Input;)Lcom/alibaba/cloud/ai/dashscope/audio/transcription/DashScopeAsrTranscriptionApiSpec$AsrTranscriptionRequest$Builder;
      26: invokestatic  #461                // Method com/alibaba/cloud/ai/dashscope/audio/transcription/DashScopeAsrTranscriptionApiSpec$AsrTranscriptionRequest$Parameters.builder:()Lcom/alibaba/cloud/ai/dashscope/audio/transcription/DashScopeAsrTranscriptionApiSpec$AsrTranscriptionRequest$Parameters$Builder;
      29: aload_2
      30: invokevirtual #466                // Method com/alibaba/cloud/ai/dashscope/audio/transcription/DashScopeAudioTranscriptionOptions.getVocabularyId:()Ljava/lang/String;
      33: invokevirtual #469                // Method com/alibaba/cloud/ai/dashscope/audio/transcription/DashScopeAsrTranscriptionApiSpec$AsrTranscriptionRequest$Parameters$Builder.vocabularyId:(Ljava/lang/String;)Lcom/alibaba/cloud/ai/dashscope/audio/transcription/DashScopeAsrTranscriptionApiSpec$AsrTranscriptionRequest$Parameters$Builder;
      36: aload_2
      37: invokevirtual #475                // Method com/alibaba/cloud/ai/dashscope/audio/transcription/DashScopeAudioTranscriptionOptions.getChannelId:()Ljava/util/List;
      40: invokevirtual #478                // Method com/alibaba/cloud/ai/dashscope/audio/transcription/DashScopeAsrTranscriptionApiSpec$AsrTranscriptionRequest$Parameters$Builder.channelId:(Ljava/util/List;)Lcom/alibaba/cloud/ai/dashscope/audio/transcription/DashScopeAsrTranscriptionApiSpec$AsrTranscriptionRequest$Parameters$Builder;
      43: aload_2
      44: invokevirtual #482                // Method com/alibaba/cloud/ai/dashscope/audio/transcription/DashScopeAudioTranscriptionOptions.getDisfluencyRemovalEnabled:()Ljava/lang/Boolean;
      47: invokevirtual #486                // Method com/alibaba/cloud/ai/dashscope/audio/transcription/DashScopeAsrTranscriptionApiSpec$AsrTranscriptionRequest$Parameters$Builder.disfluencyRemovalEnabled:(Ljava/lang/Boolean;)Lcom/alibaba/cloud/ai/dashscope/audio/transcription/DashScopeAsrTranscriptionApiSpec$AsrTranscriptionRequest$Parameters$Builder;
      50: aload_2
      51: invokevirtual #490                // Method com/alibaba/cloud/ai/dashscope/audio/transcription/DashScopeAudioTranscriptionOptions.getTimestampAlignmentEnabled:()Ljava/lang/Boolean;
      54: invokevirtual #493                // Method com/alibaba/cloud/ai/dashscope/audio/transcription/DashScopeAsrTranscriptionApiSpec$AsrTranscriptionRequest$Parameters$Builder.timestampAlignmentEnabled:(Ljava/lang/Boolean;)Lcom/alibaba/cloud/ai/dashscope/audio/transcription/DashScopeAsrTranscriptionApiSpec$AsrTranscriptionRequest$Parameters$Builder;
      57: aload_2
      58: invokevirtual #496                // Method com/alibaba/cloud/ai/dashscope/audio/transcription/DashScopeAudioTranscriptionOptions.getSpecialWordFilter:()Ljava/lang/String;
      61: invokevirtual #499                // Method com/alibaba/cloud/ai/dashscope/audio/transcription/DashScopeAsrTranscriptionApiSpec$AsrTranscriptionRequest$Parameters$Builder.specialWordFilter:(Ljava/lang/String;)Lcom/alibaba/cloud/ai/dashscope/audio/transcription/DashScopeAsrTranscriptionApiSpec$AsrTranscriptionRequest$Parameters$Builder;
      64: aload_2
      65: invokevirtual #502                // Method com/alibaba/cloud/ai/dashscope/audio/transcription/DashScopeAudioTranscriptionOptions.getDiarizationEnabled:()Ljava/lang/Boolean;
      68: invokevirtual #505                // Method com/alibaba/cloud/ai/dashscope/audio/transcription/DashScopeAsrTranscriptionApiSpec$AsrTranscriptionRequest$Parameters$Builder.diarizationEnabled:(Ljava/lang/Boolean;)Lcom/alibaba/cloud/ai/dashscope/audio/transcription/DashScopeAsrTranscriptionApiSpec$AsrTranscriptionRequest$Parameters$Builder;
      71: aload_2
      72: invokevirtual #508                // Method com/alibaba/cloud/ai/dashscope/audio/transcription/DashScopeAudioTranscriptionOptions.getLanguageHints:()Ljava/util/List;
      75: invokevirtual #511                // Method com/alibaba/cloud/ai/dashscope/audio/transcription/DashScopeAsrTranscriptionApiSpec$AsrTranscriptionRequest$Parameters$Builder.languageHints:(Ljava/util/List;)Lcom/alibaba/cloud/ai/dashscope/audio/transcription/DashScopeAsrTranscriptionApiSpec$AsrTranscriptionRequest$Parameters$Builder;
      78: aload_2
      79: invokevirtual #514                // Method com/alibaba/cloud/ai/dashscope/audio/transcription/DashScopeAudioTranscriptionOptions.getSpeakerCount:()Ljava/lang/Integer;
      82: invokevirtual #517                // Method com/alibaba/cloud/ai/dashscope/audio/transcription/DashScopeAsrTranscriptionApiSpec$AsrTranscriptionRequest$Parameters$Builder.speakerCount:(Ljava/lang/Integer;)Lcom/alibaba/cloud/ai/dashscope/audio/transcription/DashScopeAsrTranscriptionApiSpec$AsrTranscriptionRequest$Parameters$Builder;
      85: invokevirtual #521                // Method com/alibaba/cloud/ai/dashscope/audio/transcription/DashScopeAsrTranscriptionApiSpec$AsrTranscriptionRequest$Parameters$Builder.build:()Lcom/alibaba/cloud/ai/dashscope/audio/transcription/DashScopeAsrTranscriptionApiSpec$AsrTranscriptionRequest$Parameters;
      88: invokevirtual #524                // Method com/alibaba/cloud/ai/dashscope/audio/transcription/DashScopeAsrTranscriptionApiSpec$AsrTranscriptionRequest$Builder.parameters:(Lcom/alibaba/cloud/ai/dashscope/audio/transcription/DashScopeAsrTranscriptionApiSpec$AsrTranscriptionRequest$Parameters;)Lcom/alibaba/cloud/ai/dashscope/audio/transcription/DashScopeAsrTranscriptionApiSpec$AsrTranscriptionRequest$Builder;
      91: aload_2
      92: invokevirtual #528                // Method com/alibaba/cloud/ai/dashscope/audio/transcription/DashScopeAudioTranscriptionOptions.getResources:()Ljava/util/List;
      95: invokevirtual #531                // Method com/alibaba/cloud/ai/dashscope/audio/transcription/DashScopeAsrTranscriptionApiSpec$AsrTranscriptionRequest$Builder.resources:(Ljava/util/List;)Lcom/alibaba/cloud/ai/dashscope/audio/transcription/DashScopeAsrTranscriptionApiSpec$AsrTranscriptionRequest$Builder;
      98: invokevirtual #535                // Method com/alibaba/cloud/ai/dashscope/audio/transcription/DashScopeAsrTranscriptionApiSpec$AsrTranscriptionRequest$Builder.build:()Lcom/alibaba/cloud/ai/dashscope/audio/transcription/DashScopeAsrTranscriptionApiSpec$AsrTranscriptionRequest;
     101: astore_3
     102: aload_0
     103: getfield      #54                 // Field restClient:Lorg/springframework/web/client/RestClient;
     106: invokeinterface #281,  1          // InterfaceMethod org/springframework/web/client/RestClient.post:()Lorg/springframework/web/client/RestClient$RequestBodyUriSpec;
     111: ldc_w         #538                // String api/v1/services/audio/asr/transcription
     114: iconst_0
     115: anewarray     #4                  // class java/lang/Object
     118: invokeinterface #291,  3          // InterfaceMethod org/springframework/web/client/RestClient$RequestBodyUriSpec.uri:(Ljava/lang/String;[Ljava/lang/Object;)Lorg/springframework/web/client/RestClient$RequestHeadersSpec;
     123: checkcast     #297                // class org/springframework/web/client/RestClient$RequestBodySpec
     126: ldc_w         #540                // String X-DashScope-Async
     129: iconst_1
     130: anewarray     #393                // class java/lang/String
     133: dup
     134: iconst_0
     135: ldc_w         #542                // String enable
     138: aastore
     139: invokeinterface #544,  3          // InterfaceMethod org/springframework/web/client/RestClient$RequestBodySpec.header:(Ljava/lang/String;[Ljava/lang/String;)Lorg/springframework/web/client/RestClient$RequestHeadersSpec;
     144: checkcast     #297                // class org/springframework/web/client/RestClient$RequestBodySpec
     147: aload_3
     148: invokeinterface #299,  2          // InterfaceMethod org/springframework/web/client/RestClient$RequestBodySpec.body:(Ljava/lang/Object;)Lorg/springframework/web/client/RestClient$RequestBodySpec;
     153: invokeinterface #303,  1          // InterfaceMethod org/springframework/web/client/RestClient$RequestBodySpec.retrieve:()Lorg/springframework/web/client/RestClient$ResponseSpec;
     158: ldc_w         #548                // class com/alibaba/cloud/ai/dashscope/audio/transcription/DashScopeAsrTranscriptionApiSpec$AsrOutPut
     161: invokeinterface #309,  2          // InterfaceMethod org/springframework/web/client/RestClient$ResponseSpec.toEntity:(Ljava/lang/Class;)Lorg/springframework/http/ResponseEntity;
     166: astore        4
     168: aload         4
     170: invokevirtual #315                // Method org/springframework/http/ResponseEntity.getStatusCode:()Lorg/springframework/http/HttpStatusCode;
     173: invokeinterface #321,  1          // InterfaceMethod org/springframework/http/HttpStatusCode.is2xxSuccessful:()Z
     178: ifeq          213
     181: aload         4
     183: invokevirtual #327                // Method org/springframework/http/ResponseEntity.getBody:()Ljava/lang/Object;
     186: checkcast     #548                // class com/alibaba/cloud/ai/dashscope/audio/transcription/DashScopeAsrTranscriptionApiSpec$AsrOutPut
     189: invokevirtual #550                // Method com/alibaba/cloud/ai/dashscope/audio/transcription/DashScopeAsrTranscriptionApiSpec$AsrOutPut.output:()Lcom/alibaba/cloud/ai/dashscope/audio/transcription/DashScopeAsrTranscriptionApiSpec$AsrOutPut$Output;
     192: invokevirtual #554                // Method com/alibaba/cloud/ai/dashscope/audio/transcription/DashScopeAsrTranscriptionApiSpec$AsrOutPut$Output.taskId:()Ljava/lang/String;
     195: astore        5
     197: getstatic     #333                // Field log:Lorg/slf4j/Logger;
     200: ldc_w         #559                // String ASR transcription taskId: {}
     203: aload         5
     205: invokeinterface #561,  3          // InterfaceMethod org/slf4j/Logger.info:(Ljava/lang/String;Ljava/lang/Object;)V
     210: goto          231
     213: new           #347                // class java/lang/RuntimeException
     216: dup
     217: aload         4
     219: invokevirtual #315                // Method org/springframework/http/ResponseEntity.getStatusCode:()Lorg/springframework/http/HttpStatusCode;
     222: invokedynamic #565,  0            // InvokeDynamic #4:makeConcatWithConstants:(Lorg/springframework/http/HttpStatusCode;)Ljava/lang/String;
     227: invokespecial #349                // Method java/lang/RuntimeException."<init>":(Ljava/lang/String;)V
     230: athrow
     231: iconst_0
     232: istore        6
     234: iload         6
     236: bipush        30
     238: if_icmpge     492
     241: aload_0
     242: getfield      #54                 // Field restClient:Lorg/springframework/web/client/RestClient;
     245: invokeinterface #281,  1          // InterfaceMethod org/springframework/web/client/RestClient.post:()Lorg/springframework/web/client/RestClient$RequestBodyUriSpec;
     250: ldc_w         #566                // String /api/v1/tasks/{taskId}
     253: iconst_1
     254: anewarray     #4                  // class java/lang/Object
     257: dup
     258: iconst_0
     259: aload         5
     261: aastore
     262: invokeinterface #291,  3          // InterfaceMethod org/springframework/web/client/RestClient$RequestBodyUriSpec.uri:(Ljava/lang/String;[Ljava/lang/Object;)Lorg/springframework/web/client/RestClient$RequestHeadersSpec;
     267: checkcast     #297                // class org/springframework/web/client/RestClient$RequestBodySpec
     270: invokestatic  #568                // Method java/util/Collections.emptyMap:()Ljava/util/Map;
     273: invokeinterface #299,  2          // InterfaceMethod org/springframework/web/client/RestClient$RequestBodySpec.body:(Ljava/lang/Object;)Lorg/springframework/web/client/RestClient$RequestBodySpec;
     278: invokeinterface #303,  1          // InterfaceMethod org/springframework/web/client/RestClient$RequestBodySpec.retrieve:()Lorg/springframework/web/client/RestClient$ResponseSpec;
     283: ldc_w         #574                // class com/alibaba/cloud/ai/dashscope/audio/transcription/DashScopeAsrTranscriptionApiSpec$AsrResponse
     286: invokeinterface #309,  2          // InterfaceMethod org/springframework/web/client/RestClient$ResponseSpec.toEntity:(Ljava/lang/Class;)Lorg/springframework/http/ResponseEntity;
     291: astore        7
     293: aload         7
     295: invokevirtual #315                // Method org/springframework/http/ResponseEntity.getStatusCode:()Lorg/springframework/http/HttpStatusCode;
     298: invokeinterface #321,  1          // InterfaceMethod org/springframework/http/HttpStatusCode.is2xxSuccessful:()Z
     303: ifne          324
     306: new           #347                // class java/lang/RuntimeException
     309: dup
     310: aload         7
     312: invokevirtual #315                // Method org/springframework/http/ResponseEntity.getStatusCode:()Lorg/springframework/http/HttpStatusCode;
     315: invokedynamic #576,  0            // InvokeDynamic #5:makeConcatWithConstants:(Lorg/springframework/http/HttpStatusCode;)Ljava/lang/String;
     320: invokespecial #349                // Method java/lang/RuntimeException."<init>":(Ljava/lang/String;)V
     323: athrow
     324: aload         7
     326: invokevirtual #327                // Method org/springframework/http/ResponseEntity.getBody:()Ljava/lang/Object;
     329: checkcast     #574                // class com/alibaba/cloud/ai/dashscope/audio/transcription/DashScopeAsrTranscriptionApiSpec$AsrResponse
     332: invokevirtual #577                // Method com/alibaba/cloud/ai/dashscope/audio/transcription/DashScopeAsrTranscriptionApiSpec$AsrResponse.output:()Lcom/alibaba/cloud/ai/dashscope/audio/transcription/DashScopeAsrTranscriptionApiSpec$AsrResponse$Output;
     335: invokevirtual #580                // Method com/alibaba/cloud/ai/dashscope/audio/transcription/DashScopeAsrTranscriptionApiSpec$AsrResponse$Output.taskStatus:()Ljava/lang/String;
     338: astore        8
     340: ldc_w         #585                // String SUCCEEDED
     343: aload         8
     345: invokevirtual #587                // Method java/lang/String.equals:(Ljava/lang/Object;)Z
     348: ifeq          364
     351: aload_0
     352: aload         7
     354: invokevirtual #327                // Method org/springframework/http/ResponseEntity.getBody:()Ljava/lang/Object;
     357: checkcast     #574                // class com/alibaba/cloud/ai/dashscope/audio/transcription/DashScopeAsrTranscriptionApiSpec$AsrResponse
     360: invokevirtual #591                // Method parseAsrResponse:(Lcom/alibaba/cloud/ai/dashscope/audio/transcription/DashScopeAsrTranscriptionApiSpec$AsrResponse;)Lcom/alibaba/cloud/ai/dashscope/audio/transcription/DashScopeAsrTranscriptionApiSpec$DashScopeAudioAsrTranscriptionResponse;
     363: areturn
     364: ldc_w         #595                // String FAILED
     367: aload         8
     369: invokevirtual #587                // Method java/lang/String.equals:(Ljava/lang/Object;)Z
     372: ifeq          386
     375: new           #347                // class java/lang/RuntimeException
     378: dup
     379: ldc_w         #597                // String ASR transcription task failed
     382: invokespecial #349                // Method java/lang/RuntimeException."<init>":(Ljava/lang/String;)V
     385: athrow
     386: ldc_w         #599                // String PENDING
     389: aload         8
     391: invokevirtual #587                // Method java/lang/String.equals:(Ljava/lang/Object;)Z
     394: ifne          408
     397: ldc_w         #601                // String RUNNING
     400: aload         8
     402: invokevirtual #587                // Method java/lang/String.equals:(Ljava/lang/Object;)Z
     405: ifeq          441
     408: iinc          6, 1
     411: ldc2_w        #603                // long 2000l
     414: invokestatic  #605                // Method java/lang/Thread.sleep:(J)V
     417: goto          489
     420: astore        9
     422: invokestatic  #613                // Method java/lang/Thread.currentThread:()Ljava/lang/Thread;
     425: invokevirtual #617                // Method java/lang/Thread.interrupt:()V
     428: new           #347                // class java/lang/RuntimeException
     431: dup
     432: ldc_w         #620                // String ASR transcription polling interrupted
     435: aload         9
     437: invokespecial #622                // Method java/lang/RuntimeException."<init>":(Ljava/lang/String;Ljava/lang/Throwable;)V
     440: athrow
     441: getstatic     #333                // Field log:Lorg/slf4j/Logger;
     444: aload         8
     446: invokedynamic #625,  0            // InvokeDynamic #6:makeConcatWithConstants:(Ljava/lang/String;)Ljava/lang/String;
     451: invokeinterface #628,  2          // InterfaceMethod org/slf4j/Logger.warn:(Ljava/lang/String;)V
     456: iinc          6, 1
     459: ldc2_w        #603                // long 2000l
     462: invokestatic  #605                // Method java/lang/Thread.sleep:(J)V
     465: goto          489
     468: astore        9
     470: invokestatic  #613                // Method java/lang/Thread.currentThread:()Ljava/lang/Thread;
     473: invokevirtual #617                // Method java/lang/Thread.interrupt:()V
     476: new           #347                // class java/lang/RuntimeException
     479: dup
     480: ldc_w         #620                // String ASR transcription polling interrupted
     483: aload         9
     485: invokespecial #622                // Method java/lang/RuntimeException."<init>":(Ljava/lang/String;Ljava/lang/Throwable;)V
     488: athrow
     489: goto          234
     492: new           #347                // class java/lang/RuntimeException
     495: dup
     496: ldc_w         #631                // String ASR transcription timeout after 30 attempts
     499: invokespecial #349                // Method java/lang/RuntimeException."<init>":(Ljava/lang/String;)V
     502: athrow
    Exception table:
       from    to  target type
         411   417   420   Class java/lang/InterruptedException
         459   465   468   Class java/lang/InterruptedException

  public org.springframework.ai.audio.transcription.AudioTranscriptionResponse callQwenAsr(com.alibaba.cloud.ai.dashscope.audio.transcription.DashScopeAudioTranscriptionPrompt, com.alibaba.cloud.ai.dashscope.audio.transcription.DashScopeAudioTranscriptionOptions);
    Code:
       0: invokestatic  #175                // Method com/alibaba/cloud/ai/dashscope/audio/transcription/DashScopeTranscriptionApiSpec$DashScopeAudioTranscriptionRequest.builder:()Lcom/alibaba/cloud/ai/dashscope/audio/transcription/DashScopeTranscriptionApiSpec$DashScopeAudioTranscriptionRequest$Builder;
       3: aload_2
       4: invokevirtual #180                // Method com/alibaba/cloud/ai/dashscope/audio/transcription/DashScopeAudioTranscriptionOptions.getModel:()Ljava/lang/String;
       7: invokevirtual #185                // Method com/alibaba/cloud/ai/dashscope/audio/transcription/DashScopeTranscriptionApiSpec$DashScopeAudioTranscriptionRequest$Builder.model:(Ljava/lang/String;)Lcom/alibaba/cloud/ai/dashscope/audio/transcription/DashScopeTranscriptionApiSpec$DashScopeAudioTranscriptionRequest$Builder;
      10: aload_1
      11: invokevirtual #191                // Method com/alibaba/cloud/ai/dashscope/audio/transcription/DashScopeAudioTranscriptionPrompt.getMessages:()Ljava/util/List;
      14: invokevirtual #196                // Method com/alibaba/cloud/ai/dashscope/audio/transcription/DashScopeTranscriptionApiSpec$DashScopeAudioTranscriptionRequest$Builder.messages:(Ljava/util/List;)Lcom/alibaba/cloud/ai/dashscope/audio/transcription/DashScopeTranscriptionApiSpec$DashScopeAudioTranscriptionRequest$Builder;
      17: aload_2
      18: invokevirtual #735                // Method com/alibaba/cloud/ai/dashscope/audio/transcription/DashScopeAudioTranscriptionOptions.getAsrOptions:()Lcom/alibaba/cloud/ai/dashscope/audio/transcription/DashScopeAudioTranscriptionOptions$AsrOptions;
      21: invokevirtual #739                // Method com/alibaba/cloud/ai/dashscope/audio/transcription/DashScopeTranscriptionApiSpec$DashScopeAudioTranscriptionRequest$Builder.asrOptions:(Lcom/alibaba/cloud/ai/dashscope/audio/transcription/DashScopeAudioTranscriptionOptions$AsrOptions;)Lcom/alibaba/cloud/ai/dashscope/audio/transcription/DashScopeTranscriptionApiSpec$DashScopeAudioTranscriptionRequest$Builder;
      24: iconst_0
      25: invokestatic  #206                // Method java/lang/Boolean.valueOf:(Z)Ljava/lang/Boolean;
      28: invokevirtual #212                // Method com/alibaba/cloud/ai/dashscope/audio/transcription/DashScopeTranscriptionApiSpec$DashScopeAudioTranscriptionRequest$Builder.stream:(Ljava/lang/Boolean;)Lcom/alibaba/cloud/ai/dashscope/audio/transcription/DashScopeTranscriptionApiSpec$DashScopeAudioTranscriptionRequest$Builder;
      31: invokevirtual #278                // Method com/alibaba/cloud/ai/dashscope/audio/transcription/DashScopeTranscriptionApiSpec$DashScopeAudioTranscriptionRequest$Builder.build:()Lcom/alibaba/cloud/ai/dashscope/audio/transcription/DashScopeTranscriptionApiSpec$DashScopeAudioTranscriptionRequest;
      34: astore_3
      35: aload_0
      36: getfield      #54                 // Field restClient:Lorg/springframework/web/client/RestClient;
      39: invokeinterface #281,  1          // InterfaceMethod org/springframework/web/client/RestClient.post:()Lorg/springframework/web/client/RestClient$RequestBodyUriSpec;
      44: ldc_w         #743                // String compatible-mode/v1/chat/completions
      47: iconst_0
      48: anewarray     #4                  // class java/lang/Object
      51: invokeinterface #291,  3          // InterfaceMethod org/springframework/web/client/RestClient$RequestBodyUriSpec.uri:(Ljava/lang/String;[Ljava/lang/Object;)Lorg/springframework/web/client/RestClient$RequestHeadersSpec;
      56: checkcast     #297                // class org/springframework/web/client/RestClient$RequestBodySpec
      59: aload_3
      60: invokeinterface #299,  2          // InterfaceMethod org/springframework/web/client/RestClient$RequestBodySpec.body:(Ljava/lang/Object;)Lorg/springframework/web/client/RestClient$RequestBodySpec;
      65: invokeinterface #303,  1          // InterfaceMethod org/springframework/web/client/RestClient$RequestBodySpec.retrieve:()Lorg/springframework/web/client/RestClient$ResponseSpec;
      70: ldc_w         #307                // class com/alibaba/cloud/ai/dashscope/audio/transcription/DashScopeTranscriptionApiSpec$DashScopeAudioTranscriptionResponse
      73: invokeinterface #309,  2          // InterfaceMethod org/springframework/web/client/RestClient$ResponseSpec.toEntity:(Ljava/lang/Class;)Lorg/springframework/http/ResponseEntity;
      78: astore        4
      80: aload         4
      82: invokevirtual #315                // Method org/springframework/http/ResponseEntity.getStatusCode:()Lorg/springframework/http/HttpStatusCode;
      85: invokeinterface #321,  1          // InterfaceMethod org/springframework/http/HttpStatusCode.is2xxSuccessful:()Z
      90: ifeq          102
      93: aload         4
      95: invokevirtual #327                // Method org/springframework/http/ResponseEntity.getBody:()Ljava/lang/Object;
      98: checkcast     #331                // class org/springframework/ai/audio/transcription/AudioTranscriptionResponse
     101: areturn
     102: getstatic     #333                // Field log:Lorg/slf4j/Logger;
     105: aload         4
     107: invokevirtual #315                // Method org/springframework/http/ResponseEntity.getStatusCode:()Lorg/springframework/http/HttpStatusCode;
     110: invokedynamic #745,  0            // InvokeDynamic #7:makeConcatWithConstants:(Lorg/springframework/http/HttpStatusCode;)Ljava/lang/String;
     115: invokeinterface #341,  2          // InterfaceMethod org/slf4j/Logger.error:(Ljava/lang/String;)V
     120: new           #347                // class java/lang/RuntimeException
     123: dup
     124: aload         4
     126: invokevirtual #315                // Method org/springframework/http/ResponseEntity.getStatusCode:()Lorg/springframework/http/HttpStatusCode;
     129: invokedynamic #745,  0            // InvokeDynamic #7:makeConcatWithConstants:(Lorg/springframework/http/HttpStatusCode;)Ljava/lang/String;
     134: invokespecial #349                // Method java/lang/RuntimeException."<init>":(Ljava/lang/String;)V
     137: athrow

  public reactor.core.publisher.Flux<org.springframework.ai.audio.transcription.AudioTranscriptionResponse> streamQwenAsr(com.alibaba.cloud.ai.dashscope.audio.transcription.DashScopeAudioTranscriptionPrompt, com.alibaba.cloud.ai.dashscope.audio.transcription.DashScopeAudioTranscriptionOptions);
    Code:
       0: invokestatic  #175                // Method com/alibaba/cloud/ai/dashscope/audio/transcription/DashScopeTranscriptionApiSpec$DashScopeAudioTranscriptionRequest.builder:()Lcom/alibaba/cloud/ai/dashscope/audio/transcription/DashScopeTranscriptionApiSpec$DashScopeAudioTranscriptionRequest$Builder;
       3: aload_2
       4: invokevirtual #180                // Method com/alibaba/cloud/ai/dashscope/audio/transcription/DashScopeAudioTranscriptionOptions.getModel:()Ljava/lang/String;
       7: invokevirtual #185                // Method com/alibaba/cloud/ai/dashscope/audio/transcription/DashScopeTranscriptionApiSpec$DashScopeAudioTranscriptionRequest$Builder.model:(Ljava/lang/String;)Lcom/alibaba/cloud/ai/dashscope/audio/transcription/DashScopeTranscriptionApiSpec$DashScopeAudioTranscriptionRequest$Builder;
      10: aload_1
      11: invokevirtual #191                // Method com/alibaba/cloud/ai/dashscope/audio/transcription/DashScopeAudioTranscriptionPrompt.getMessages:()Ljava/util/List;
      14: invokevirtual #196                // Method com/alibaba/cloud/ai/dashscope/audio/transcription/DashScopeTranscriptionApiSpec$DashScopeAudioTranscriptionRequest$Builder.messages:(Ljava/util/List;)Lcom/alibaba/cloud/ai/dashscope/audio/transcription/DashScopeTranscriptionApiSpec$DashScopeAudioTranscriptionRequest$Builder;
      17: aload_2
      18: invokevirtual #735                // Method com/alibaba/cloud/ai/dashscope/audio/transcription/DashScopeAudioTranscriptionOptions.getAsrOptions:()Lcom/alibaba/cloud/ai/dashscope/audio/transcription/DashScopeAudioTranscriptionOptions$AsrOptions;
      21: invokevirtual #739                // Method com/alibaba/cloud/ai/dashscope/audio/transcription/DashScopeTranscriptionApiSpec$DashScopeAudioTranscriptionRequest$Builder.asrOptions:(Lcom/alibaba/cloud/ai/dashscope/audio/transcription/DashScopeAudioTranscriptionOptions$AsrOptions;)Lcom/alibaba/cloud/ai/dashscope/audio/transcription/DashScopeTranscriptionApiSpec$DashScopeAudioTranscriptionRequest$Builder;
      24: iconst_1
      25: invokestatic  #206                // Method java/lang/Boolean.valueOf:(Z)Ljava/lang/Boolean;
      28: invokevirtual #212                // Method com/alibaba/cloud/ai/dashscope/audio/transcription/DashScopeTranscriptionApiSpec$DashScopeAudioTranscriptionRequest$Builder.stream:(Ljava/lang/Boolean;)Lcom/alibaba/cloud/ai/dashscope/audio/transcription/DashScopeTranscriptionApiSpec$DashScopeAudioTranscriptionRequest$Builder;
      31: aload_2
      32: invokevirtual #351                // Method com/alibaba/cloud/ai/dashscope/audio/transcription/DashScopeAudioTranscriptionOptions.getStreamOptions:()Lcom/alibaba/cloud/ai/dashscope/audio/transcription/DashScopeAudioTranscriptionOptions$StreamOptions;
      35: invokevirtual #355                // Method com/alibaba/cloud/ai/dashscope/audio/transcription/DashScopeTranscriptionApiSpec$DashScopeAudioTranscriptionRequest$Builder.streamOptions:(Lcom/alibaba/cloud/ai/dashscope/audio/transcription/DashScopeAudioTranscriptionOptions$StreamOptions;)Lcom/alibaba/cloud/ai/dashscope/audio/transcription/DashScopeTranscriptionApiSpec$DashScopeAudioTranscriptionRequest$Builder;
      38: invokevirtual #278                // Method com/alibaba/cloud/ai/dashscope/audio/transcription/DashScopeTranscriptionApiSpec$DashScopeAudioTranscriptionRequest$Builder.build:()Lcom/alibaba/cloud/ai/dashscope/audio/transcription/DashScopeTranscriptionApiSpec$DashScopeAudioTranscriptionRequest;
      41: astore_3
      42: ldc_w         #359                // String [DONE]
      45: invokedynamic #361,  0            // InvokeDynamic #2:test:(Ljava/lang/String;)Ljava/util/function/Predicate;
      50: astore        4
      52: aload_0
      53: getfield      #72                 // Field webClient:Lorg/springframework/web/reactive/function/client/WebClient;
      56: invokeinterface #365,  1          // InterfaceMethod org/springframework/web/reactive/function/client/WebClient.post:()Lorg/springframework/web/reactive/function/client/WebClient$RequestBodyUriSpec;
      61: ldc_w         #743                // String compatible-mode/v1/chat/completions
      64: iconst_0
      65: anewarray     #4                  // class java/lang/Object
      68: invokeinterface #370,  3          // InterfaceMethod org/springframework/web/reactive/function/client/WebClient$RequestBodyUriSpec.uri:(Ljava/lang/String;[Ljava/lang/Object;)Lorg/springframework/web/reactive/function/client/WebClient$RequestHeadersSpec;
      73: checkcast     #375                // class org/springframework/web/reactive/function/client/WebClient$RequestBodySpec
      76: aload_3
      77: invokestatic  #377                // Method reactor/core/publisher/Mono.just:(Ljava/lang/Object;)Lreactor/core/publisher/Mono;
      80: ldc_w         #307                // class com/alibaba/cloud/ai/dashscope/audio/transcription/DashScopeTranscriptionApiSpec$DashScopeAudioTranscriptionResponse
      83: invokeinterface #385,  3          // InterfaceMethod org/springframework/web/reactive/function/client/WebClient$RequestBodySpec.body:(Ljava/lang/Object;Ljava/lang/Class;)Lorg/springframework/web/reactive/function/client/WebClient$RequestHeadersSpec;
      88: invokeinterface #388,  1          // InterfaceMethod org/springframework/web/reactive/function/client/WebClient$RequestHeadersSpec.retrieve:()Lorg/springframework/web/reactive/function/client/WebClient$ResponseSpec;
      93: ldc_w         #393                // class java/lang/String
      96: invokeinterface #395,  2          // InterfaceMethod org/springframework/web/reactive/function/client/WebClient$ResponseSpec.bodyToFlux:(Ljava/lang/Class;)Lreactor/core/publisher/Flux;
     101: aload         4
     103: invokevirtual #401                // Method reactor/core/publisher/Flux.takeUntil:(Ljava/util/function/Predicate;)Lreactor/core/publisher/Flux;
     106: aload         4
     108: invokeinterface #407,  1          // InterfaceMethod java/util/function/Predicate.negate:()Ljava/util/function/Predicate;
     113: invokevirtual #413                // Method reactor/core/publisher/Flux.filter:(Ljava/util/function/Predicate;)Lreactor/core/publisher/Flux;
     116: aload_0
     117: invokedynamic #746,  0            // InvokeDynamic #8:apply:(Lcom/alibaba/cloud/ai/dashscope/api/DashScopeAudioTranscriptionApi;)Ljava/util/function/Function;
     122: invokevirtual #420                // Method reactor/core/publisher/Flux.map:(Ljava/util/function/Function;)Lreactor/core/publisher/Flux;
     125: areturn

  public com.alibaba.cloud.ai.dashscope.api.DashScopeAudioTranscriptionApi$Builder mutate();
    Code:
       0: new           #747                // class com/alibaba/cloud/ai/dashscope/api/DashScopeAudioTranscriptionApi$Builder
       3: dup
       4: aload_0
       5: invokespecial #749                // Method com/alibaba/cloud/ai/dashscope/api/DashScopeAudioTranscriptionApi$Builder."<init>":(Lcom/alibaba/cloud/ai/dashscope/api/DashScopeAudioTranscriptionApi;)V
       8: areturn

  public java.lang.String getBaseUrl();
    Code:
       0: aload_0
       1: getfield      #9                  // Field baseUrl:Ljava/lang/String;
       4: areturn

  public java.lang.String getWebsocketUrl();
    Code:
       0: aload_0
       1: getfield      #15                 // Field websocketUrl:Ljava/lang/String;
       4: areturn

  public org.springframework.ai.model.ApiKey getApiKey();
    Code:
       0: aload_0
       1: getfield      #18                 // Field apiKey:Lorg/springframework/ai/model/ApiKey;
       4: areturn

  public java.lang.String getWorkSpaceId();
    Code:
       0: aload_0
       1: getfield      #22                 // Field workSpaceId:Ljava/lang/String;
       4: areturn

  public org.springframework.util.MultiValueMap<java.lang.String, java.lang.String> getHeaders();
    Code:
       0: aload_0
       1: getfield      #25                 // Field headers:Lorg/springframework/util/MultiValueMap;
       4: areturn

  public static com.alibaba.cloud.ai.dashscope.api.DashScopeAudioTranscriptionApi$Builder builder();
    Code:
       0: new           #747                // class com/alibaba/cloud/ai/dashscope/api/DashScopeAudioTranscriptionApi$Builder
       3: dup
       4: invokespecial #752                // Method com/alibaba/cloud/ai/dashscope/api/DashScopeAudioTranscriptionApi$Builder."<init>":()V
       7: areturn

  static {};
    Code:
       0: ldc           #10                 // class com/alibaba/cloud/ai/dashscope/api/DashScopeAudioTranscriptionApi
       2: invokestatic  #774                // Method org/slf4j/LoggerFactory.getLogger:(Ljava/lang/Class;)Lorg/slf4j/Logger;
       5: putstatic     #333                // Field log:Lorg/slf4j/Logger;
       8: return
}
